croudtech_bootstrap_app/__init__.py
croudtech_bootstrap_app/__main__.py
croudtech_bootstrap_app/bootstrap.py
croudtech_bootstrap_app/cli.py
croudtech_bootstrap_app/croudtech-bootstrap.py
croudtech_bootstrap_app/logging.py
croudtech_bootstrap_app/metrics.py
croudtech_bootstrap_app/redis_config.py
croudtech_bootstrap_app/tests/__init__.py
croudtech_bootstrap_app/tests/bootstrap_test.py
croudtech_bootstrap_app/tests/test_values/TestEnv1/TestApp.secret.yaml
croudtech_bootstrap_app/tests/test_values/TestEnv1/TestApp.yaml
croudtech_bootstrap_app/tests/test_values/TestEnv1/common.secret.yaml
croudtech_bootstrap_app/tests/test_values/TestEnv1/common.yaml
croudtech_bootstrap_app/tests/test_values/TestEnv2/TestApp.secret.yaml
croudtech_bootstrap_app/tests/test_values/TestEnv2/TestApp.yaml
croudtech_bootstrap_app/tests/test_values/TestEnv2/common.secret.yaml
croudtech_bootstrap_app/tests/test_values/TestEnv2/common.yaml
croudtech_bootstrap-0.1.56.dist-info/METADATA
croudtech_bootstrap-0.1.56.dist-info/WHEEL
croudtech_bootstrap-0.1.56.dist-info/entry_points.txt
croudtech_bootstrap-0.1.56.dist-info/RECORD
