Metadata-Version: 2.1
Name: croudtech-bootstrap
Version: 0.1.56
Summary: Applicaton config via AWS S3 and AWS Secrets Manager
License: MIT
Author: Jim Robinson
Author-email: jscrobinson@gmail.com
Requires-Python: >=3.9,<3.14
Classifier: License :: OSI Approved :: MIT License
Classifier: Programming Language :: Python :: 3
Classifier: Programming Language :: Python :: 3.9
Classifier: Programming Language :: Python :: 3.10
Classifier: Programming Language :: Python :: 3.11
Classifier: Programming Language :: Python :: 3.12
Classifier: Programming Language :: Python :: 3.13
Requires-Dist: boto3 (>=1.35.41,<2.0.0)
Requires-Dist: click (>=8.1.7,<9.0.0)
Requires-Dist: pyyaml (>=6.0.2,<7.0.0)
Requires-Dist: redis (==5.0.4)
Requires-Dist: table2ascii (>=1.1.3,<2.0.0)
